ga4gh/__init__.py
ga4gh/drs/__init__.py
ga4gh/drs/entrypoint.py
ga4gh/drs/cli/__init__.py
ga4gh/drs/cli/methods/__init__.py
ga4gh/drs/cli/methods/get.py
ga4gh/drs/cli/methods/schemes.py
ga4gh/drs/cli/parsing/__init__.py
ga4gh/drs/cli/parsing/get.py
ga4gh/drs/cli/parsing/schemes.py
ga4gh/drs/config/__init__.py
ga4gh/drs/config/access_methods.py
ga4gh/drs/config/checksum_status.py
ga4gh/drs/config/constants.py
ga4gh/drs/config/download_status.py
ga4gh/drs/config/global_state.py
ga4gh/drs/config/loglevels.py
ga4gh/drs/definitions/__init__.py
ga4gh/drs/definitions/access_method.py
ga4gh/drs/definitions/access_url.py
ga4gh/drs/definitions/checksum.py
ga4gh/drs/definitions/object.py
ga4gh/drs/exceptions/__init__.py
ga4gh/drs/exceptions/drs_exceptions.py
ga4gh/drs/resources/__init__.py
ga4gh/drs/resources/supported_schemes.yml
ga4gh/drs/routes/__init__.py
ga4gh/drs/routes/route.py
ga4gh/drs/routes/route_fetch_bytes.py
ga4gh/drs/routes/route_object_info.py
ga4gh/drs/util/__init__.py
ga4gh/drs/util/data_accessor.py
ga4gh/drs/util/download_manager.py
ga4gh/drs/util/download_tree.py
ga4gh/drs/util/logger.py
ga4gh/drs/util/functions/__init__.py
ga4gh/drs/util/functions/hashfunc.py
ga4gh/drs/util/functions/http.py
ga4gh/drs/util/functions/logging.py
ga4gh/drs/util/functions/url.py
ga4gh/drs/util/method_types/__init__.py
ga4gh/drs/util/method_types/gs.py
ga4gh/drs/util/method_types/http.py
ga4gh/drs/util/method_types/https.py
ga4gh/drs/util/method_types/method_type.py
ga4gh/drs/util/validators/__init__.py
ga4gh/drs/util/validators/get_cli_validator.py
ga4gh_drs_client-0.1.7.dist-info/LICENSE.md
ga4gh_drs_client-0.1.7.dist-info/METADATA
ga4gh_drs_client-0.1.7.dist-info/WHEEL
ga4gh_drs_client-0.1.7.dist-info/entry_points.txt
ga4gh_drs_client-0.1.7.dist-info/top_level.txt
ga4gh_drs_client-0.1.7.dist-info/RECORD
