Metadata-Version: 2.1
Name: ga4gh-drs-client
Version: 0.1.7
Summary: Retrieve omics data from Data Repository Service (DRS) web services
Home-page: https://github.com/ga4gh/ga4gh-drs-client
Author: Jeremy Adams
Author-email: jeremy.adams@ga4gh.org
License: UNKNOWN
Platform: UNKNOWN
Classifier: Programming Language :: Python :: 3.6
Classifier: Programming Language :: Python :: 3.7
Classifier: License :: OSI Approved :: MIT License
Classifier: Operating System :: OS Independent
Classifier: Natural Language :: English
Classifier: Topic :: Scientific/Engineering :: Bio-Informatics
Requires-Dist: click (>=7.0)
Requires-Dist: crc32c (>=1.7)
Requires-Dist: PyYAML (>=5.1.2)
Requires-Dist: requests (>=2.22.0)
Requires-Dist: tqdm (>=4.35.0)
